{
  "hash": "4aecdad0",
  "configHash": "d9f7a87b",
  "lockfileHash": "e3b0c442",
  "browserHash": "8ac708a8",
  "optimized": {
    "@mui/material": {
      "src": "../../node_modules/@mui/material/index.js",
      "file": "@mui_material.js",
      "fileHash": "302642ec",
      "needsInterop": false
    },
    "@mui/material/styles": {
      "src": "../../node_modules/@mui/material/styles/index.js",
      "file": "@mui_material_styles.js",
      "fileHash": "88a77170",
      "needsInterop": false
    },
    "@mui/material/Typography": {
      "src": "../../node_modules/@mui/material/Typography/index.js",
      "file": "@mui_material_Typography.js",
      "fileHash": "2d5f2c02",
      "needsInterop": false
    },
    "axios": {
      "src": "../../node_modules/axios/index.js",
      "file": "axios.js",
      "fileHash": "ede8ced2",
      "needsInterop": false
    },
    "prop-types": {
      "src": "../../node_modules/prop-types/index.js",
      "file": "prop-types.js",
      "fileHash": "5bc0e7ed",
      "needsInterop": true
    },
    "react": {
      "src": "../../node_modules/react/index.js",
      "file": "react.js",
      "fileHash": "a125c09b",
      "needsInterop": true
    },
    "react-dom/client": {
      "src": "../../node_modules/react-dom/client.js",
      "file": "react-dom_client.js",
      "fileHash": "586155ee",
      "needsInterop": true
    },
    "react-infinite-scroll-component": {
      "src": "../../node_modules/react-infinite-scroll-component/dist/index.es.js",
      "file": "react-infinite-scroll-component.js",
      "fileHash": "fad8f955",
      "needsInterop": false
    }
  },
  "chunks": {
    "chunk-G5ARPTUW": {
      "file": "chunk-G5ARPTUW.js"
    },
    "chunk-C76LW4QG": {
      "file": "chunk-C76LW4QG.js"
    },
    "chunk-4TS22AV2": {
      "file": "chunk-4TS22AV2.js"
    },
    "chunk-ZNVVQF6B": {
      "file": "chunk-ZNVVQF6B.js"
    },
    "chunk-JMVEG3FK": {
      "file": "chunk-JMVEG3FK.js"
    },
    "chunk-TWJRYSII": {
      "file": "chunk-TWJRYSII.js"
    },
    "chunk-DC5AMYBS": {
      "file": "chunk-DC5AMYBS.js"
    }
  }
}